segmentation_models/__init__.py
segmentation_models/__version__.py
segmentation_models/losses.py
segmentation_models/metrics.py
segmentation_models/utils.py
segmentation_models/backbones/__init__.py
segmentation_models/backbones/backbones_factory.py
segmentation_models/backbones/inception_resnet_v2.py
segmentation_models/backbones/inception_v3.py
segmentation_models/base/__init__.py
segmentation_models/base/functional.py
segmentation_models/base/objects.py
segmentation_models/models/__init__.py
segmentation_models/models/_common_blocks.py
segmentation_models/models/_utils.py
segmentation_models/models/fpn.py
segmentation_models/models/linknet.py
segmentation_models/models/pspnet.py
segmentation_models/models/unet.py
segmentation_models_zwy-1.0.2.dist-info/LICENSE
segmentation_models_zwy-1.0.2.dist-info/METADATA
segmentation_models_zwy-1.0.2.dist-info/WHEEL
segmentation_models_zwy-1.0.2.dist-info/top_level.txt
segmentation_models_zwy-1.0.2.dist-info/RECORD
